ecg_feature_selection/__init__.py
ecg_feature_selection/ecg_feature_selection.py
ecg_feature_selection-1.2.1.data/scripts/ecg_feature_selection.py
ecg_feature_selection-1.2.1.dist-info/METADATA
ecg_feature_selection-1.2.1.dist-info/RECORD
ecg_feature_selection-1.2.1.dist-info/WHEEL
ecg_feature_selection-1.2.1.dist-info/top_level.txt
